eddi/__init__.py
eddi/core/__init__.py
eddi-0.1.0.dist-info/METADATA
eddi-0.1.0.dist-info/WHEEL
eddi-0.1.0.dist-info/licenses/LICENSE
eddi-0.1.0.dist-info/RECORD
