Metadata-Version: 2.4
Name: eddi
Version: 0.1.0
Summary: Interactive lighting system with pose-driven control and AI-powered sequencing
Project-URL: Homepage, https://github.com/mrilikecoding/eddi
Project-URL: Repository, https://github.com/mrilikecoding/eddi
Project-URL: Documentation, https://github.com/mrilikecoding/eddi#readme
Project-URL: Issues, https://github.com/mrilikecoding/eddi/issues
Project-URL: Changelog, https://github.com/mrilikecoding/eddi/blob/main/CHANGELOG.md
Author-email: Eddi Contributors <noreply@github.com>
License: MIT License
License-File: LICENSE
Classifier: Development Status :: 4 - Beta
Classifier: License :: OSI Approved :: MIT License
Classifier: Operating System :: OS Independent
Classifier: Programming Language :: Python :: 3
Classifier: Programming Language :: Python :: 3.11
Classifier: Programming Language :: Python :: 3.12
Requires-Python: >=3.11
Provides-Extra: dev
Requires-Dist: pytest>=7.4.0; extra == 'dev'
